<output><sentence id="0"><allSent>'''Subjektívny idealizmus''' je [[filozofický smer]], ktorého predstavitelia odmietajú oprávnenost tézy o existencii [[objektívna realita|objektívnej reality]] [[Platón]]ovej.</allSent><linkLabel>filozofický smer</linkLabel><lemma>filozofický smer</lemma><wklnk>http://sk.wikipedia.org/wiki/filozofický_smer</wklnk><dblnk>http://sk.dbpedia.org/resource/filozofický_smer</dblnk><abstract></abstract><type></type><vc></vc><linkLabel>objektívnej reality</linkLabel><lemma>objektívna realita</lemma><wklnk>http://sk.wikipedia.org/wiki/objektívna_realita</wklnk><dblnk>http://sk.dbpedia.org/resource/objektívna_realita</dblnk><abstract></abstract><type></type><vc></vc><linkLabel>Platónovej</linkLabel><lemma>Platón</lemma><wklnk>http://sk.wikipedia.org/wiki/Platón</wklnk><dblnk>http://sk.dbpedia.org/resource/Platón</dblnk><abstract></abstract><type></type><vc></vc></sentence><sentence id="1"><allSent>'''Konfucianizmus''' = '''konfuciánstvo''' je [[filozofický smer]] - jedna z dvoch vetví osobitného [[Cína (civilizácia)|cínskeho]] polonáboženského kultu univerza a obcianskych cností; prúd cínskej filozofie spájaný s osobou [[Konfucius|Konfucia]], ktorý už nezastáva vieru vo viacerých bohov, vyhýba sa metafyzickým otázkam, pestuje skôr obciansky kult a moralistné normovanie vlastností užitocných pre štát.</allSent><linkLabel>filozofický smer</linkLabel><lemma>filozofický smer</lemma><wklnk>http://sk.wikipedia.org/wiki/filozofický_smer</wklnk><dblnk>http://sk.dbpedia.org/resource/filozofický_smer</dblnk><abstract></abstract><type></type><vc></vc><linkLabel>Konfucia</linkLabel><lemma>Konfucius</lemma><wklnk>http://sk.wikipedia.org/wiki/Konfucius</wklnk><dblnk>http://sk.dbpedia.org/resource/Konfucius</dblnk><abstract></abstract><type>Filozof</type><vc></vc></sentence></output>